setup.py
src/pysubpub.egg-info/PKG-INFO
src/pysubpub.egg-info/SOURCES.txt
src/pysubpub.egg-info/dependency_links.txt
src/pysubpub.egg-info/not-zip-safe
src/pysubpub.egg-info/top_level.txt
src/subpub/__init__.py
src/subpub/main.py
src/tests/__init__.py
src/tests/test1.py
src/tests/test2.py
src/tests/test3.py