Metadata-Version: 1.1
Name: pysubpub
Version: 0.2.0
Summary: Publish-Subscribe framework
Home-page: https://github.com/jldupont/pysubpub
Author: Jean-Lou Dupont
Author-email: jl@jldupont.com
License: UNKNOWN
Platform: UNKNOWN
Classifier: Development Status :: 4 - Beta
Classifier: Programming Language :: Python
Classifier: Intended Audience :: Developers
Classifier: Topic :: Utilities
